README.rst
setup.cfg
setup.py
socialstyrelsen/__init__.py
socialstyrelsen/exceptions.py
socialstyrelsen/scraper.py
socialstyrelsen_scraper.egg-info/PKG-INFO
socialstyrelsen_scraper.egg-info/SOURCES.txt
socialstyrelsen_scraper.egg-info/dependency_links.txt
socialstyrelsen_scraper.egg-info/not-zip-safe
socialstyrelsen_scraper.egg-info/requires.txt
socialstyrelsen_scraper.egg-info/top_level.txt