Metadata-Version: 1.1
Name: socialstyrelsen-scraper
Version: 0.0.2
Summary: A scraper of statistical data from socialstyrelsen.se built on top of Statscraper.
Home-page: https://github.com/jplusplus/socialstyrelsen-scraper
Author: Jens Finnäs
Author-email: jens.finnas@gmail.com
License: MIT
Download-URL: https://github.com/jplusplus/socialstyrelsen-scraper/archive/0.0.2.tar.gz
Platform: UNKNOWN
